<?xml version="1.0" ?>
<annotation>
  <folder>image</folder>
  <filename>000016.jpeg</filename>
  <path>./content/image/000016.jpeg</path>
  <source>
    <database>Unknown</database>
  </source>
  <size>
    <width>800</width>
    <height>800</height>
    <depth>3</depth>
  </size>
  <segmented>0</segmented>
  <object>
    <name>USB</name>
    <pose>Unspecified</pose>
    <truncated>0</truncated>
    <difficult>0</difficult>
    <bndbox>
      <xmin>260</xmin>
      <ymin>360</ymin>
      <xmax>351</xmax>
      <ymax>422</ymax>
    </bndbox>
  </object>
  <object>
    <name>USB</name>
    <pose>Unspecified</pose>
    <truncated>0</truncated>
    <difficult>0</difficult>
    <bndbox>
      <xmin>370</xmin>
      <ymin>367</ymin>
      <xmax>456</xmax>
      <ymax>422</ymax>
    </bndbox>
  </object>
  <object>
    <name>DISPLAYPORT</name>
    <pose>Unspecified</pose>
    <truncated>0</truncated>
    <difficult>0</difficult>
    <bndbox>
      <xmin>475</xmin>
      <ymin>365</ymin>
      <xmax>591</xmax>
      <ymax>425</ymax>
    </bndbox>
  </object>
  <object>
    <name>AUDIO</name>
    <pose>Unspecified</pose>
    <truncated>0</truncated>
    <difficult>0</difficult>
    <bndbox>
      <xmin>612</xmin>
      <ymin>355</ymin>
      <xmax>687</xmax>
      <ymax>420</ymax>
    </bndbox>
  </object>
</annotation>
